[
  {
    "title": "Getting Started with SwiftUI",
    "postId": "101",
    "videoURL": "https://example.com/videos/swiftui-intro.mp4",
    "metrics": {
      "views": 45,
      "likes": 5
    }
  },
  {
    "title": "iOS Development Best Practices",
    "postId": "102",
    "videoURL": "https://example.com/videos/best-practices.mp4",
    "metrics": {
      "views": 38,
      "likes": 4
    }
  },
  {
    "title": "Advanced Swift Techniques",
    "postId": "103",
    "videoURL": "https://example.com/videos/advanced-swift.mp4",
    "metrics": {
      "views": 32,
      "likes": 3
    }
  },
  {
    "title": "Building Custom Views",
    "postId": "104",
    "videoURL": "https://example.com/videos/custom-views.mp4",
    "metrics": {
      "views": 26,
      "likes": 2
    }
  },
  {
    "title": "App Performance Optimization",
    "postId": "105",
    "videoURL": "https://example.com/videos/performance.mp4",
    "metrics": {
      "views": 20,
      "likes": 2
    }
  },
  {
    "title": "Debugging Like a Pro",
    "postId": "106",
    "videoURL": "https://example.com/videos/debugging.mp4",
    "metrics": {
      "views": 15,
      "likes": 1
    }
  }
]
